mux.v
module modMux2Entrada(
    entrada1, 
    entrada2, 
    out, 
    controle
    );

    input [31:0] entrada1, 
    entrada2;

    output [31:0] out;

    input controle;

    assign out = 
    (controle == 1'b0) 
    ? entrada1 : entrada2;

endmodule

memoriaDeDados.v
/*module teste_tb;
    reg _lerMemoria, 
    _escreverNaMemoria;

    reg _clock;

    reg [31:0] _endereco, 
    _dadosEscrita;

    wire [31:0] _lerDados;

    memoriaDeDados dm(_clock, 
    _lerMemoria, 
    _escreverNaMemoria, 
    _endereco, 
    _dadosEscrita, 
    _lerDados
    );

    initial _clock = 0;

    always #5 _clock <= !(_clock);

    initial begin
        $dumpfile("test.vcd");
        $dumpvars(2,teste_tb);
        $dumpvars(0,dm.memoriaDeDados[0]);
        $dumpvars(0,dm.memoriaDeDados[1]);
        $dumpvars(0,dm.memoriaDeDados[2]);
        _lerMemoria <= 0; _escreverNaMemoria = 1;
        _endereco = 0;
        _dadosEscrita = 32'b1101;
        #10
        _endereco = 4;
        _dadosEscrita = 32'b111;
        #10 
        _lerMemoria = 1; _escreverNaMemoria = 0; 
        _endereco = 0;
        #10
        $display("%b", _lerDados);
        _endereco = 4;
        #10
        $display("%b", _lerDados);
        #200 $finish;
    end

endmodule*/

module memoriaDeDados(
    clock, 
    lerMemoria, 
    escreverNaMemoria, 
    endereco, 
    dadosEscrita, 
    lerDados
    );

    input clock, 
    lerMemoria, 
    escreverNaMemoria;

    input [31:0] endereco, 
    dadosEscrita;

    output reg [31:0] lerDados;

    reg [31:0] memoriaDeDados [0:512];


    always @(*)
    begin
        if (lerMemoria) lerDados 
        = memoriaDeDados[endereco[31:2]];
    end

    always @(negedge clock)
    begin
        if (escreverNaMemoria) memoriaDeDados[endereco[31:2]] 
        <= dadosEscrita;
    end
    
endmodule

alu.v
/*module alu_tb;
    reg [31:0] 
    aluentrada1_, 
    aluentrada2_;

    reg [3:0] ControleDeAlu_;

    wire [31:0] rusultadoDaAlu_;

    wire zeroo_;

    alu alutb(
    aluentrada1_, 
    aluentrada2_, 
    ControleDeAlu_, 
    rusultadoDaAlu_, 
    zeroo_
    );

    initial begin
        $dumpfile("teste.vcd");
        $dumpvars(2, alu_tb);
        #5 ControleDeAlu_ 
        <= 4'b0010; aluentrada1_ 
        <= 32'hFFFFFFFF; aluentrada2_ 
        <= 32'h2;

        #5 ControleDeAlu_ 
        <= 4'b0110; aluentrada1_ 
        <= 32'h5; aluentrada2_ 
        <= 32'hFFFFFFFF;

        #5 ControleDeAlu_ 
        <= 4'b0011; aluentrada1_ 
        <= 32'h0; aluentrada2_ 
        <= 32'hFFFFFFFF;

        #5 ControleDeAlu_ 
        <= 4'b0100; aluentrada1_ 
        <= 32'hFFFFFFFF; aluentrada2_ 
        <= 32'h9;

        #5 $finish;
    end
endmodule*/

module alu(
    aluentrada1, 
    aluentrada2, 
    ControleDeAlu, 
    rusultadoDaAlu, 
    zeroo
    );

    input [31:0] 
    aluentrada1, 
    aluentrada2;

    input [3:0] ControleDeAlu;

    output reg [31:0] rusultadoDaAlu;

    output zeroo;

    assign zeroo = (rusultadoDaAlu == 0) ? 1 : 0;

    always @(*)
    begin
        case (ControleDeAlu)
            4'b0010: rusultadoDaAlu 
            <= aluentrada1 + aluentrada2;// adicionar

            4'b0110: rusultadoDaAlu 
            <= aluentrada1 - aluentrada2;// sub

            4'b0011: rusultadoDaAlu 
            <= aluentrada1 ^ aluentrada2;// xor

            4'b0100: rusultadoDaAlu 
            <= aluentrada1 >> aluentrada2;// srl

            default: rusultadoDaAlu <= 31'bx;
        endcase
    end
endmodule

adicionar.v
module adicionar(
    x, 
    y, 
    saida
    );

    input[31:0] 
    x, 
    y;

    output[31:0] saida;

    assign saida = x + y;
endmodule

controleDaAlu.v
/*module test_tb;
    wire [3:0] alucontroleAcontrole_;

    reg [1:0] aluOpAcontrole_;
    
    reg [3:0] f3f7Acontrole_;

    controleDaAlu controleDaAlu(
    f3f7Acontrole_, 
    aluOpAcontrole_, 
    alucontroleAcontrole_
    );

    initial begin
        $dumpfile("test.vcd");
        $dumpvars(2,test_tb);
        #5 aluOpAcontrole_ <= 2'b00; f3f7Acontrole_ <= 4'b1000;
        #5 aluOpAcontrole_ <= 2'b10; f3f7Acontrole_ <= 4'b1101;
        #5 aluOpAcontrole_ <= 2'b01; f3f7Acontrole_ <= 4'b1000;
        #5 $finish;
    end
    
endmodule*/

module controleDaAlu(
    f3f7Acontrole, 
    aluOpAcontrole, 
    alucontroleAcontrole
    );

    output reg [3:0] alucontroleAcontrole;

    input [1:0] aluOpAcontrole;

    input [3:0] f3f7Acontrole;

    wire funct7Acontrole;

    wire [2:0] funct3Acontrole;

    assign funct7Acontrole = f3f7Acontrole[3];

    assign funct3Acontrole = f3f7Acontrole[2:0];

    always @(*)
    begin
        case (aluOpAcontrole)
            2'b00: alucontroleAcontrole 
            <= 4'b0010; // 00 - adicionar (addi, lw, sw)

            2'b01: alucontroleAcontrole 
            <= 4'b0110; // 01 - sub (beq)

            2'b10: begin
                case (funct3Acontrole)
                
                    3'b000: alucontroleAcontrole 
                    <= 4'b0110; // sub (sub)

                    3'b100: alucontroleAcontrole 
                    <= 4'b0011; // xor (xor)

                    3'b101: alucontroleAcontrole 
                    <= 4'b0100; // srl (srl)

                endcase
            end
        endcase
    end
endmodule

geradorImediato.v
/*module G_imm_tb;
    reg [31:0] instr_;

    wire [31:0] GImm_;

    G_imm imG(
        instr_,
        GImm_
        );

    initial begin
        $dumpfile("teste.vcd");

        $dumpvars(2, G_imm_tb);

        instr_ <= 32'h03052283;

        #5 instr_ <= 32'h00552023;
        #5 instr_ <= 32'h00552823;
        #5 instr_ <= 32'h80230293;
        #5 instr_ <= 32'b01111111100001001000111111100011;
        #5 instr_ <= 32'b11111111100001001000111111100011;

        #5 $finish;
    end
endmodule*/

module G_imm(
    instr, 
    GImm
    );

    input [31:0] instr;

    output reg [31:0] GImm;

    always @(instr)
    begin
        case (instr[6:0])

            7'b0000011: GImm 
            <= {{21{instr[31]}}, 
            instr[30:20]}; // lw - I

            7'b0100011: GImm 
            <= {{21{instr[31]}}, 
            instr[30:25], 
            instr[11:7]}; // sw - S

            7'b0010011: GImm 
            <= {{21{instr[31]}}, 
            instr[30:20]}; // addi - I

            7'b1100011: GImm 
            <= {{20{instr[31]}}, 
            instr[7], 
            instr[30:25], 
            instr[11:8], 
            {1{1'b0}}}; // beq - SB

            default: GImm <= 32'bx;
        endcase
    end
endmodule

memoriaRegistro.v
//`timescale 1ns/1ps
module registerMem_tb;
    reg _clock, _registradorDeEscrita;

    reg [4:0] _lerRegistrador1, 
    _lerRegistrador2, 
    _idRegistradorEscrita;

    reg [31:0] _dadoWr;

    wire [31:0] _dadoLeitura, 
    _dadoLeitura2;

    registerMem rm(
    _clock, 
    _registradorDeEscrita, 
    _lerRegistrador1, 
    _lerRegistrador2, 
    _idRegistradorEscrita, 
    _dadoWr, 
    _dadoLeitura, 
    _dadoLeitura2
    );

    initial begin 
        _clock <= 0; 
        _registradorDeEscrita = 1;
    end

    always #1 _clock <=(!_clock);

    initial begin
        #10 _registradorDeEscrita = 1; 
        _idRegistradorEscrita = 5; 
        _dadoWr = 50; 

        #10 _lerRegistrador1 = 5; 
        _registradorDeEscrita = 0;

        #100 $finish;
    end

endmodule

module registerMem(
    clock, 
    registradorDeEscrita, 
    lerRegistrador1, 
    lerRegistrador2, 
    idRegistradorEscrita, 
    dadoWr,
    dadoLeitura, 
    dadoLeitura2
    );

    input clock, 
    registradorDeEscrita;

    input [4:0] lerRegistrador1, 
    lerRegistrador2, 
    idRegistradorEscrita;

    input [31:0] dadoWr;

    output reg [31:0] dadoLeitura, 
    dadoLeitura2;

    reg [31:0] registradores [0:31];

    integer i;

    initial begin
        for (i = 0; i < 32; i = i +1) begin
            registradores[i] = 0;
        end
    end

    always @(registradores[0]) registradores[0] = 0;

    always @(posedge clock) begin

        if (registradorDeEscrita == 1) 
        registradores[idRegistradorEscrita] <= dadoWr;
        
    end

    always @(lerRegistrador1, registradores[lerRegistrador1]) 

    begin
        dadoLeitura 
        <= registradores[lerRegistrador1];
    end

    always @(lerRegistrador2, registradores[lerRegistrador1])

    begin
        dadoLeitura2 
        <= registradores[lerRegistrador2];
    end

endmodule

control.v
/*module teste;
    wire Branchcontrole_, 
    lermemControle_, 
    MemToRegC_, 
    memoriaDeEscritaC_, 
    ALUSrc_, 
    registradorDeEscritaC_;

    wire [1:0] controlealuop_;

    reg [6:0] Instrucaocontrole_;

    control controle(Instrucaocontrole_, 
    Branchcontrole_, 
    lermemControle_, 
    MemToRegC_, 
    controlealuop_, 
    memoriaDeEscritaC_, 
    ALUSrc_, 
    registradorDeEscritaC_
    );

    initial begin
        $dumpfile("test.vcd");
        $dumpvars(2,teste);
        #5 Instrucaocontrole_ <= 7'b0000011;
        #5 Instrucaocontrole_ <= 7'b0110011;
        #5 $finish;
    end
endmodule*/

module control(
    Instrucaocontrole, 
    Branchcontrole, 
    lermemControle, 
    MemToRegC,
    controlealuop, 
    memoriaDeEscritaC, 
    ALUSrc, 
    registradorDeEscritaC
    );

    input [6:0] Instrucaocontrole;

    output Branchcontrole, 
    lermemControle, 
    MemToRegC, 
    memoriaDeEscritaC, 
    ALUSrc, 
    registradorDeEscritaC;

    output [1:0] controlealuop;

    reg [7:0] controleSaida;

    assign {ALUSrc, 
    MemToRegC, 
    registradorDeEscritaC, 
    lermemControle, 
    memoriaDeEscritaC, 
    Branchcontrole, 
    controlealuop} = controleSaida;

    always @(Instrucaocontrole)
    begin
        case (Instrucaocontrole)
            7'b0000011: controleSaida 
            <=  8'b11110000; // lw   - I

            7'b0100011: controleSaida 
            <=  8'b10001000; // sw   - S

            7'b0110011: controleSaida 
            <=  8'b00100010; // sub, xor, srl  - R

            7'b0010011: controleSaida 
            <=  8'b10100000; // addi - I

            7'b1100011: controleSaida 
            <=  8'b00000101; // beq  - SB

            default: controleSaida <=  8'bxxxxxxxx;
        endcase
    end
endmodule

memoriaDeInstrucao.v
/*module teste_tb;
    reg [31:0] _EnderecoDeLeitura;

    reg [8*25:0] _nomeArquivo;

    wire [31:0] _Instrucao;

    memoriaDeInstrucao im(_EnderecoDeLeitura, 
    _nomeArquivo, 
    _Instrucao
    );

    initial begin
        _nomeArquivo = "testetxt.txt";
        _EnderecoDeLeitura = 8;
    end

endmodule*/

module memoriaDeInstrucao(
    EnderecoDeLeitura, 
    nomeArquivo, 
    Instrucao, 
    arquivoFinalDele
    );

    input [31:0] EnderecoDeLeitura;

    input [8*25:0] nomeArquivo;

    output reg [31:0] Instrucao;

    output reg arquivoFinalDele;

    integer arquivo;
    integer error;
    reg [31:0] linha;

    always @(nomeArquivo)

    begin

        arquivo 
        = $fopen(nomeArquivo, "r");

    end

    always @(EnderecoDeLeitura)

    begin

        if (EnderecoDeLeitura 
            === 32'bx) begin

            Instrucao = 0;
            arquivoFinalDele = 1;

        end
        else begin

            error 
            = $fseek(arquivo, EnderecoDeLeitura*8 + EnderecoDeLeitura/4, 0);

            error 
            = $fscanf(arquivo, "%b", linha);

            if (error != -1) 
            Instrucao = linha;

            else Instrucao = 0;
        end
    end
endmodule

pc.v
module pc(
    entradaDoPc, 
    saidaDoPc, 
    clock, 
    pcReset
    );

    input [31:0] entradaDoPc;

    input clock, pcReset;

    output [31:0] saidaDoPc;

    reg [31:0] saidaDoPc;
    
    always @(posedge clock)

        if (!pcReset) saidaDoPc <= 0;

        else saidaDoPc <= entradaDoPc;
        
endmodule

caminhoDeDados.v
`timescale 1ns/1ps

module datapath_tb;
    reg CDclock_, 
    CDreset_;

    reg [8*25:0] nomeArquivoInstDP_;

    integer error;

    integer i;

    reg signed [31:0] valorReg;

    wire fimArquivo;

    caminhoDeDadosRiscV dpR5(
    CDclock_, 
    CDreset_, 
    nomeArquivoInstDP_, 
    fimArquivo
    );

    initial begin
        nomeArquivoInstDP_ = "inputs/input3.txt";
        $dumpfile("saidas/testeCaminho.vcd");
        $dumpvars(3, datapath_tb);
    end

    initial CDclock_ <= 0;
    always #1 CDclock_ <=(!CDclock_);

    always #1 begin
        if (fimArquivo) begin
            for (i = 0; i < 32; i = i + 1) begin
                valorReg = dpR5.regMem.registradores[i];
                if (valorReg[31])
                    $display("registrador |%2d|: %15d <decimal<| %b <binario>", i, valorReg, valorReg);
                else
                    $display("registrador |%2d|: %15d <decimal>| %b <binario>", i, valorReg, valorReg);
            end
            $finish;
        end
    end

    initial begin
        CDreset_ <= 0;
        #5 CDreset_ <= 1;
        #100 CDreset_ <= 0;
    end

endmodule

module caminhoDeDadosRiscV(
    CDclock, 
    CDreset, 
    CDnomeArquivo, 
    fimArquivo
    );

    input [8*25:0] CDnomeArquivo;

    input CDclock, 
    CDreset;

    wire [31:0] CDentradaPc, 
    CDsaidaPc, 
    CDinstrucao, 
    CDG_imediatoSaida, 
    CDsoma4Saida,
    CDsomaDesvio, 
    CDleituraDados, 
    CDleituraDados2, 
    CDmuxAluSaida, 
    CDaluSaida, 
    CDleituraMemoria, 
    CDdadosEscritaReg;

    wire CDdesvio, 
    CDleituraMem, 
    CDmemoriaParaReg, 
    CDescritaMem, 
    CDaluSrc, 
    CDescritaRegistrador,
    CDaluZero, 
    CDsaidaE;

    wire [1:0] CDaluOp;
    wire [3:0] CDcontroleAlu;
    wire [3:0] CDcontroleF3F7Alu;
    output fimArquivo;

    assign CDsaidaE = CDdesvio & CDaluZero;
    assign CDcontroleF3F7Alu = {CDinstrucao[30], CDinstrucao[14:12]};

    pc pcDP(CDentradaPc, CDsaidaPc, CDclock, CDreset);

    memoriaDeInstrucao insMem(CDsaidaPc, CDnomeArquivo, CDinstrucao, fimArquivo); // 

    control controleDP(CDinstrucao[6:0], CDdesvio, CDleituraMem, CDmemoriaParaReg, CDaluOp,
     CDescritaMem, CDaluSrc, CDescritaRegistrador);

    registerMem regMem(CDclock, CDescritaRegistrador, CDinstrucao[19:15], CDinstrucao[24:20],
     CDinstrucao[11:7], CDdadosEscritaReg, CDleituraDados, CDleituraDados2); //

    G_imm G_imm(CDinstrucao, CDG_imediatoSaida); //

    controleDaAlu controleDaAlu(CDcontroleF3F7Alu, CDaluOp, CDcontroleAlu); //

    adicionar add4(32'h4, CDsaidaPc, CDsoma4Saida);

    adicionar addBranch(CDsaidaPc, CDG_imediatoSaida, CDsomaDesvio);

    alu alu(CDleituraDados, CDmuxAluSaida, CDcontroleAlu, CDaluSaida, CDaluZero);

    memoriaDeDados dataMem(CDclock, CDleituraMem, CDescritaMem, CDaluSaida, CDleituraDados2, CDleituraMemoria);

    modMux2Entrada muxAdds(CDsoma4Saida, CDsomaDesvio, CDentradaPc, CDsaidaE);

    modMux2Entrada muxAlu(CDleituraDados2, CDG_imediatoSaida, CDmuxAluSaida, CDaluSrc);

    modMux2Entrada muxDataMem(CDaluSaida, CDleituraMemoria, CDdadosEscritaReg, CDmemoriaParaReg);

endmodule

saidas/testeCaminho.vcd
$date
	Fri Aug 09 21:56:54 2024
$end
$version
	Icarus Verilog
$end
$timescale
	1ps
$end
$scope module datapath_tb $end
$var wire 1 ! fimArquivo $end
$var reg 1 " CDclock_ $end
$var reg 1 # CDreset_ $end
$var reg 201 $ nomeArquivoInstDP_ [200:0] $end
$var reg 32 % valorReg [31:0] $end
$var integer 32 & i [31:0] $end
$scope module dpR5 $end
$var wire 1 " CDclock $end
$var wire 201 ' CDnomeArquivo [200:0] $end
$var wire 1 # CDreset $end
$var wire 1 ( CDsaidaE $end
$var wire 1 ! fimArquivo $end
$var wire 32 ) CDsomaDesvio [31:0] $end
$var wire 32 * CDsoma4Saida [31:0] $end
$var wire 32 + CDsaidaPc [31:0] $end
$var wire 32 , CDmuxAluSaida [31:0] $end
$var wire 1 - CDmemoriaParaReg $end
$var wire 32 . CDleituraMemoria [31:0] $end
$var wire 1 / CDleituraMem $end
$var wire 32 0 CDleituraDados2 [31:0] $end
$var wire 32 1 CDleituraDados [31:0] $end
$var wire 32 2 CDinstrucao [31:0] $end
$var wire 1 3 CDescritaRegistrador $end
$var wire 1 4 CDescritaMem $end
$var wire 32 5 CDentradaPc [31:0] $end
$var wire 1 6 CDdesvio $end
$var wire 32 7 CDdadosEscritaReg [31:0] $end
$var wire 4 8 CDcontroleF3F7Alu [3:0] $end
$var wire 4 9 CDcontroleAlu [3:0] $end
$var wire 1 : CDaluZero $end
$var wire 1 ; CDaluSrc $end
$var wire 32 < CDaluSaida [31:0] $end
$var wire 2 = CDaluOp [1:0] $end
$var wire 32 > CDG_imediatoSaida [31:0] $end
$scope module G_imm $end
$var wire 32 ? instr [31:0] $end
$var reg 32 @ GImm [31:0] $end
$upscope $end
$scope module add4 $end
$var wire 32 A x [31:0] $end
$var wire 32 B y [31:0] $end
$var wire 32 C saida [31:0] $end
$upscope $end
$scope module addBranch $end
$var wire 32 D y [31:0] $end
$var wire 32 E x [31:0] $end
$var wire 32 F saida [31:0] $end
$upscope $end
$scope module alu $end
$var wire 1 : zeroo $end
$var wire 32 G aluentrada2 [31:0] $end
$var wire 32 H aluentrada1 [31:0] $end
$var wire 4 I ControleDeAlu [3:0] $end
$var reg 32 J rusultadoDaAlu [31:0] $end
$upscope $end
$scope module controleDP $end
$var wire 7 K Instrucaocontrole [6:0] $end
$var wire 1 3 registradorDeEscritaC $end
$var wire 1 4 memoriaDeEscritaC $end
$var wire 1 / lermemControle $end
$var wire 2 L controlealuop [1:0] $end
$var wire 1 - MemToRegC $end
$var wire 1 6 Branchcontrole $end
$var wire 1 ; ALUSrc $end
$var reg 8 M controleSaida [7:0] $end
$upscope $end
$scope module controleDaAlu $end
$var wire 2 N aluOpAcontrole [1:0] $end
$var wire 4 O f3f7Acontrole [3:0] $end
$var wire 1 P funct7Acontrole $end
$var wire 3 Q funct3Acontrole [2:0] $end
$var reg 4 R alucontroleAcontrole [3:0] $end
$upscope $end
$scope module dataMem $end
$var wire 1 " clock $end
$var wire 32 S endereco [31:0] $end
$var wire 1 4 escreverNaMemoria $end
$var wire 1 / lerMemoria $end
$var wire 32 T dadosEscrita [31:0] $end
$var reg 32 U lerDados [31:0] $end
$upscope $end
$scope module insMem $end
$var wire 201 V nomeArquivo [200:0] $end
$var wire 32 W EnderecoDeLeitura [31:0] $end
$var reg 32 X Instrucao [31:0] $end
$var reg 1 ! arquivoFinalDele $end
$var reg 32 Y linha [31:0] $end
$var integer 32 Z arquivo [31:0] $end
$var integer 32 [ error [31:0] $end
$upscope $end
$scope module muxAdds $end
$var wire 1 ( controle $end
$var wire 32 \ entrada1 [31:0] $end
$var wire 32 ] entrada2 [31:0] $end
$var wire 32 ^ out [31:0] $end
$upscope $end
$scope module muxAlu $end
$var wire 1 ; controle $end
$var wire 32 _ entrada2 [31:0] $end
$var wire 32 ` out [31:0] $end
$var wire 32 a entrada1 [31:0] $end
$upscope $end
$scope module muxDataMem $end
$var wire 1 - controle $end
$var wire 32 b entrada1 [31:0] $end
$var wire 32 c entrada2 [31:0] $end
$var wire 32 d out [31:0] $end
$upscope $end
$scope module pcDP $end
$var wire 1 " clock $end
$var wire 32 e entradaDoPc [31:0] $end
$var wire 1 # pcReset $end
$var reg 32 f saidaDoPc [31:0] $end
$upscope $end
$scope module regMem $end
$var wire 1 " clock $end
$var wire 32 g dadoWr [31:0] $end
$var wire 5 h idRegistradorEscrita [4:0] $end
$var wire 5 i lerRegistrador1 [4:0] $end
$var wire 5 j lerRegistrador2 [4:0] $end
$var wire 1 3 registradorDeEscrita $end
$var reg 32 k dadoLeitura [31:0] $end
$var reg 32 l dadoLeitura2 [31:0] $end
$var integer 32 m i [31:0] $end
$upscope $end
$upscope $end
$upscope $end
$enddefinitions $end
$comment Show the parameter values. $end
$dumpall
$end
#0
$dumpvars
b100000 m
bx l
bx k
bx j
bx i
bx h
bx g
bx f
bx e
bx d
bx c
bx b
bx a
bx `
bx _
bx ^
bx ]
bx \
bx [
b10000000000000000000000000000011 Z
bx Y
bx X
bx W
b110100101101110011100000111010101110100011100110010111101101001011011100111000001110101011101000011001100101110011101000111100001110100 V
bx U
bx T
bx S
bx R
bx Q
xP
bx O
bx N
bx M
bx L
bx K
bx J
bx I
bx H
bx G
bx F
bx E
bx D
bx C
bx B
b100 A
bx @
bx ?
bx >
bx =
bx <
x;
x:
bx 9
bx 8
bx 7
x6
bx 5
x4
x3
bx 2
bx 1
bx 0
x/
bx .
x-
bx ,
bx +
bx *
bx )
x(
b110100101101110011100000111010101110100011100110010111101101001011011100111000001110101011101000011001100101110011101000111100001110100 '
bx &
bx %
b110100101101110011100000111010101110100011100110010111101101001011011100111000001110101011101000011001100101110011101000111100001110100 $
0#
0"
x!
$end
#1000
0:
b101010 7
b101010 d
b101010 g
b10 9
b10 I
b10 R
b101010 <
b101010 J
b101010 S
b101010 b
0(
1;
0-
13
0/
04
06
b0 =
b0 L
b0 N
b100 5
b100 ^
b100 e
b101010 ,
b101010 G
b101010 `
b0 1
b0 H
b0 k
b0 0
b0 T
b0 a
b0 l
b10100000 M
b101010 )
b101010 F
b101010 ]
b101010 >
b101010 @
b101010 D
b101010 _
b0 Q
0P
b1 h
b1010 j
b10 i
b10011 K
b0 8
b0 O
b10101000010000000010010011 2
b10101000010000000010010011 ?
b10101000010000000010010011 X
b10101000010000000010010011 Y
b1 [
b100 *
b100 C
b100 \
b0 +
b0 B
b0 E
b0 W
b0 f
1"
#2000
0"
#3000
1"
#4000
0"
#5000
1:
b0 7
b0 d
b0 g
b110 9
b110 I
b110 R
b0 <
b0 J
b0 S
b0 b
0;
b10 =
b10 L
b10 N
b0 ,
b0 G
b0 `
b100010 M
bx >
bx @
bx D
bx _
1P
b11 h
b101 j
b100 i
b110011 K
b1000 8
b1000 O
b1000 5
b1000 ^
b1000 e
b1000000010100100000000110110011 2
b1000000010100100000000110110011 ?
b1000000010100100000000110110011 X
b1000000010100100000000110110011 Y
b1 [
bx )
bx F
bx ]
b1000 *
b1000 C
b1000 \
b100 +
b100 B
b100 E
b100 W
b100 f
1"
1#
#6000
0"
#7000
b11 9
b11 I
b11 R
b100 Q
0P
b110 h
b1000 j
b111 i
b100 8
b100 O
b1100 5
b1100 ^
b1100 e
b100000111100001100110011 2
b100000111100001100110011 ?
b100000111100001100110011 X
b100000111100001100110011 Y
b1 [
b1100 *
b1100 C
b1100 \
b1000 +
b1000 B
b1000 E
b1000 W
b1000 f
1"
#8000
0"
#9000
b10 9
b10 I
b10 R
1;
03
14
b0 =
b0 L
b0 N
b10001000 M
b1100 )
b1100 F
b1100 ]
b0 >
b0 @
b0 D
b0 _
b10 Q
b0 h
b110 j
b1010 i
b100011 K
b10 8
b10 O
b10000 5
b10000 ^
b10000 e
b11001010010000000100011 2
b11001010010000000100011 ?
b11001010010000000100011 X
b11001010010000000100011 Y
b1 [
b10000 *
b10000 C
b10000 \
b1100 +
b1100 B
b1100 E
b1100 W
b1100 f
1"
#10000
0"
#11000
0:
b101101 7
b101101 d
b101101 g
b101101 <
b101101 J
b101101 S
b101101 b
13
04
b11 ,
b11 G
b11 `
b101010 1
b101010 H
b101010 k
b10100000 M
b11 >
b11 @
b11 D
b11 _
b0 Q
b100 h
b11 j
b1 i
b10011 K
b0 8
b0 O
b10100 5
b10100 ^
b10100 e
b1100001000001000010011 2
b1100001000001000010011 ?
b1100001000001000010011 X
b1100001000001000010011 Y
b1 [
b10011 )
b10011 F
b10011 ]
b10100 *
b10100 C
b10100 \
b10000 +
b10000 B
b10000 E
b10000 W
b10000 f
1"
#12000
0"
#13000
b10000000 7
b10000000 d
b10000000 g
b10000000 <
b10000000 J
b10000000 S
b10000000 b
03
14
b10000000 ,
b10000000 G
b10000000 `
b0 1
b0 H
b0 k
b10001000 M
b10000000 >
b10000000 @
b10000000 D
b10000000 _
b10 Q
b0 h
b1011 j
b1100 i
b100011 K
b10 8
b10 O
b11000 5
b11000 ^
b11000 e
b1000101101100010000000100011 2
b1000101101100010000000100011 ?
b1000101101100010000000100011 X
b1000101101100010000000100011 Y
b1 [
b10010100 )
b10010100 F
b10010100 ]
b11000 *
b11000 C
b11000 \
b10100 +
b10100 B
b10100 E
b10100 W
b10100 f
1"
#14000
0"
#15000
b111 7
b111 d
b111 g
b111 <
b111 J
b111 S
b111 b
13
04
b111 ,
b111 G
b111 `
b10100000 M
b111 >
b111 @
b111 D
b111 _
b0 Q
b100 h
b111 j
b10 i
b10011 K
b0 8
b0 O
b11100 5
b11100 ^
b11100 e
b11100010000001000010011 2
b11100010000001000010011 ?
b11100010000001000010011 X
b11100010000001000010011 Y
b1 [
b11111 )
b11111 F
b11111 ]
b11100 *
b11100 C
b11100 \
b11000 +
b11000 B
b11000 E
b11000 W
b11000 f
1"
#16000
0"
#17000
b11111111111111111111111111110110 7
b11111111111111111111111111110110 d
b11111111111111111111111111110110 g
b11111111111111111111111111110110 <
b11111111111111111111111111110110 J
b11111111111111111111111111110110 S
b11111111111111111111111111110110 b
b11111111111111111111111111110110 ,
b11111111111111111111111111110110 G
b11111111111111111111111111110110 `
b11111111111111111111111111110110 >
b11111111111111111111111111110110 @
b11111111111111111111111111110110 D
b11111111111111111111111111110110 _
1P
b1101 h
b10110 j
b1110 i
b1000 8
b1000 O
b100000 5
b100000 ^
b100000 e
b11111111011001110000011010010011 2
b11111111011001110000011010010011 ?
b11111111011001110000011010010011 X
b11111111011001110000011010010011 Y
b1 [
b10010 )
b10010 F
b10010 ]
b100000 *
b100000 C
b100000 \
b11100 +
b11100 B
b11100 E
b11100 W
b11100 f
1"
#18000
0"
#19000
1:
b0 7
b0 d
b0 g
b110 9
b110 I
b110 R
b0 <
b0 J
b0 S
b0 b
0;
b10 =
b10 L
b10 N
b0 ,
b0 G
b0 `
b100010 M
bx >
bx @
bx D
bx _
b1111 h
b10001 j
b10000 i
b110011 K
b100100 5
b100100 ^
b100100 e
b1000001000110000000011110110011 2
b1000001000110000000011110110011 ?
b1000001000110000000011110110011 X
b1000001000110000000011110110011 Y
b1 [
bx )
bx F
bx ]
b100100 *
b100100 C
b100100 \
b100000 +
b100000 B
b100000 E
b100000 W
b100000 f
1"
#20000
0"
#21000
b11 9
b11 I
b11 R
b100 Q
0P
b10010 h
b10100 j
b10011 i
b100 8
b100 O
b101000 5
b101000 ^
b101000 e
b1010010011100100100110011 2
b1010010011100100100110011 ?
b1010010011100100100110011 X
b1010010011100100100110011 Y
b1 [
b101000 *
b101000 C
b101000 \
b100100 +
b100100 B
b100100 E
b100100 W
b100100 f
1"
#22000
0"
#23000
b0 <
b0 J
b0 S
b0 b
b10 9
b10 I
b10 R
b0 ,
b0 G
b0 `
1;
03
14
b0 =
b0 L
b0 N
b101010 0
b101010 T
b101010 a
b101010 l
b10001000 M
b101000 )
b101000 F
b101000 ]
b0 >
b0 @
b0 D
b0 _
b10 Q
b0 h
b1 j
b10110 i
b100011 K
b10 8
b10 O
b101100 5
b101100 ^
b101100 e
b110110010000000100011 2
b110110010000000100011 ?
b110110010000000100011 X
b110110010000000100011 Y
b1 [
b101100 *
b101100 C
b101100 \
b101000 +
b101000 B
b101000 E
b101000 W
b101000 f
1"
#24000
0"
#25000
b101010 7
b101010 d
b101010 g
b101010 .
b101010 U
b101010 c
1-
13
1/
04
b0 0
b0 T
b0 a
b0 l
b11110000 M
b10101 h
b0 j
b11 K
b110000 5
b110000 ^
b110000 e
b10110010101010000011 2
b10110010101010000011 ?
b10110010101010000011 X
b10110010101010000011 Y
b1 [
b101100 )
b101100 F
b101100 ]
b110000 *
b110000 C
b110000 \
b101100 +
b101100 B
b101100 E
b101100 W
b101100 f
1"
#26000
0"
#27000
0:
b1 <
b1 J
b1 S
b1 b
b1 7
b1 d
b1 g
0-
0/
b1 ,
b1 G
b1 `
b101010 0
b101010 T
b101010 a
b101010 l
b10100000 M
b1 >
b1 @
b1 D
b1 _
b0 Q
b1 h
b1 j
b10 i
b10011 K
b0 8
b0 O
b110100 5
b110100 ^
b110100 e
b100010000000010010011 2
b100010000000010010011 ?
b100010000000010010011 X
b100010000000010010011 Y
b1 [
b110001 )
b110001 F
b110001 ]
b110100 *
b110100 C
b110100 \
b110000 +
b110000 B
b110000 E
b110000 W
b110000 f
1"
#28000
0"
#29000
b11111111111111111111111111111111 7
b11111111111111111111111111111111 d
b11111111111111111111111111111111 g
b11111111111111111111111111111111 <
b11111111111111111111111111111111 J
b11111111111111111111111111111111 S
b11111111111111111111111111111111 b
b11111111111111111111111111111111 ,
b11111111111111111111111111111111 G
b11111111111111111111111111111111 `
b0 0
b0 T
b0 a
b0 l
b11111111111111111111111111111111 >
b11111111111111111111111111111111 @
b11111111111111111111111111111111 D
b11111111111111111111111111111111 _
1P
b11111 j
b1000 8
b1000 O
b111000 5
b111000 ^
b111000 e
b11111111111100010000000010010011 2
b11111111111100010000000010010011 ?
b11111111111100010000000010010011 X
b11111111111100010000000010010011 Y
b1 [
b110011 )
b110011 F
b110011 ]
b111000 *
b111000 C
b111000 \
b110100 +
b110100 B
b110100 E
b110100 W
b110100 f
1"
#30000
0"
#31000
1:
b0 7
b0 d
b0 g
b11 9
b11 I
b11 R
b0 <
b0 J
b0 S
b0 b
0;
b10 =
b10 L
b10 N
b0 ,
b0 G
b0 `
b100010 M
bx >
bx @
bx D
bx _
b100 Q
0P
b1011 h
b1010 j
b1001 i
b110011 K
b100 8
b100 O
b111100 5
b111100 ^
b111100 e
b101001001100010110110011 2
b101001001100010110110011 ?
b101001001100010110110011 X
b101001001100010110110011 Y
b1 [
bx )
bx F
bx ]
b111100 *
b111100 C
b111100 \
b111000 +
b111000 B
b111000 E
b111000 W
b111000 f
1"
#32000
0"
